{
  "settings": {
    "analysis": {
      "analyzer": {
        "stemming_analyzer": {
          "tokenizer": "standard",
          "filter": ["standard", "lowercase", "possessive_english_stemmer", "light_english_stemmer"]
        }
      },
      "filter": {
        "light_english_stemmer": {
          "type": "stemmer",
          "name": "light_english"
        },
        "possessive_english_stemmer": {
          "type": "stemmer",
          "name": "possessive_english"
        }
      }
    }
  },
  "mappings": {
    "services": {
      "_meta": {
      },
      "dynamic": "strict",
      "properties": {
        "id": {
          "type": "string",
          "index": "not_analyzed"
        },
        "lot": {
          "type": "string",
          "index": "not_analyzed",
          "fields": {
            "raw": {"type": "string", "index": "not_analyzed"}
          }
        },
        "lotName": {
          "type": "string",
          "index": "analyzed"
        },
        "frameworkName": {
          "type": "string",
          "index": "not_analyzed"
        },
        "serviceName": {
          "type": "string"
        },
        "serviceDescription": {
          "term_vector" : "with_positions_offsets",
          "type": "string",
          "analyzer": "stemming_analyzer"
        },
        "serviceBenefits": {
          "type": "string",
          "analyzer": "stemming_analyzer"
        },
        "serviceFeatures": {
          "type": "string",
          "analyzer": "stemming_analyzer"
        },
        "supplierName": {
          "type": "string"
        },
        "filter_lot": {
          "type": "string",
          "index": "not_analyzed"
        },
        "serviceCategories": {
          "type": "string",
          "analyzer": "stemming_analyzer",
          "fields": {
            "raw": {"type": "string", "index": "not_analyzed"}
          }
        },
        "filter_serviceCategories": {
          "type": "string",
          "index": "not_analyzed"
        },
        "filter_cloudDeploymentModel": {
          "type": "string",
          "index": "not_analyzed"
        },
        "filter_resellingType": {
          "type": "string",
          "index": "not_analyzed"
        },
        "filter_emailOrTicketingSupport": {
          "type": "string",
          "index": "not_analyzed"
        },
        "filter_phoneSupport": {
          "type": "string",
          "index": "not_analyzed"
        },
        "filter_webChatSupport": {
          "type": "string",
          "index": "not_analyzed"
        },
        "filter_onsiteSupport": {
          "type": "string",
          "index": "not_analyzed"
        },
        "filter_browsersAccess": {
          "type": "string",
          "index": "not_analyzed"
        },
        "filter_installation": {
          "type": "string",
          "index": "not_analyzed"
        },
        "filter_mobile": {
          "type": "string",
          "index": "not_analyzed"
        },
        "filter_APISoftware": {
          "type": "string",
          "index": "not_analyzed"
        },
        "filter_metricsHow": {
          "type": "string",
          "index": "not_analyzed"
        },
        "filter_metricsWhat": {
          "type": "string",
          "index": "not_analyzed"
        },
        "filter_scalingType": {
          "type": "string",
          "index": "not_analyzed"
        }, 
        "filter_usageNotifications": {
          "type": "string",
          "index": "not_analyzed"
        },
        "filter_backup": {
          "type": "string",
          "index": "not_analyzed"
        },
        "filter_backupDatacentre": {
          "type": "string",
          "index": "not_analyzed"
        },
        "filter_publicSectorNetworksTypes": {
          "type": "string",
          "index": "not_analyzed"
        },
        "filter_dataProtectionBetweenNetworks": {
          "type": "string",
          "index": "not_analyzed"
        },
        "filter_dataProtectionWithinNetwork": {
          "type": "string",
          "index": "not_analyzed"
        },
        "filter_dataStorageAndProcessingLocations": {
          "type": "string",
          "index": "not_analyzed"
        },
        "filter_userAuthentication": {
          "type": "string",
          "index": "not_analyzed"
        },
        "filter_managementAccessAuthentication": {
          "type": "string",
          "index": "not_analyzed"
        },
        "filter_standardsISOIEC27001": {
          "type": "string",
          "index": "not_analyzed"
        },
        "filter_standardsISO28000": {
          "type": "string",
          "index": "not_analyzed"
        },
        "filter_standardsCSASTAR": {
          "type": "string",
          "index": "not_analyzed"
        },
        "filter_standardsPCI": {
          "type": "string",
          "index": "not_analyzed"
        },
        "filter_securityGovernanceStandards": {
          "type": "string",
          "index": "not_analyzed"
        },
        "filter_datacentreSecurityStandards": {
          "type": "string",
          "index": "not_analyzed"
        },
        "filter_staffSecurityClearanceChecks": {
          "type": "string",
          "index": "not_analyzed"
        },
        "filter_governmentSecurityClearances": {
          "type": "string",
          "index": "not_analyzed"
        },
        "filter_educationPricing": {
          "type": "string",
          "index": "not_analyzed"
        },
        "filter_freeVersionTrialOption": {
          "type": "string",
          "index": "not_analyzed"
        }
      }
    }
  }
}
